<?xml version="1.0" encoding="utf-8" standalone="no"?>

<VebProdavnica>
  
  <Proizvod>
    <Kategorija>Laptop</Kategorija>
    <Cena valuta="RSD">138878</Cena>
    <TekstOglasa>Laptop Notebook računari</TekstOglasa>
    <Oznaka>Laptop Huawei 53010UHU/CD60 13"/Intel Core i5/8 GB/512 GB/Windows 10 Home 64</Oznaka>
    <Akcija cena="124990" datumIsteka="2021-01-7">10%</Akcija>
  </Proizvod>

  <Proizvod>
    <Kategorija>Laptop</Kategorija>
    <Cena valuta="RSD">122211</Cena>
    <TekstOglasa>Laptop Notebook računari</TekstOglasa>
    <Oznaka>HP laptop 1U6C2EA 15,6"/AMD Ryzen 5/8 GB/512 GB SSD</Oznaka>
    <Akcija cena="109990" datumIsteka="2021-01-7">10%</Akcija>
  </Proizvod>

  <Proizvod>
    <Kategorija>Monitor</Kategorija>
    <Cena valuta="RSD">24449</Cena>
    <TekstOglasa>Gaming monitor</TekstOglasa>
    <Oznaka>ACER/23.6"/Full HD 1920 x 1080</Oznaka>
    <Akcija/>
  </Proizvod>

  <Proizvod>
    <Kategorija>Monitor</Kategorija>
    <Cena valuta="RSD">33339</Cena>
    <TekstOglasa>UltraWide monitor</TekstOglasa>
    <Oznaka>LG/UltraWide 29"/UWHD 2560 x 1080</Oznaka>
    <Akcija cena="29999" datumIsteka="2021-01-7">10%</Akcija>
  </Proizvod>
  
</VebProdavnica>